metrics/__init__.py
metrics/filters.py
metrics/halstead.py
metrics/parser.py
metrics/raw.py
metrics_felbeaver-0.0.1.dist-info/LICENSE
metrics_felbeaver-0.0.1.dist-info/METADATA
metrics_felbeaver-0.0.1.dist-info/WHEEL
metrics_felbeaver-0.0.1.dist-info/top_level.txt
metrics_felbeaver-0.0.1.dist-info/RECORD
