Metadata-Version: 2.1
Name: metrics-felbeaver
Version: 0.0.1
Summary: A Python library for computing various software metrics from the source code
Home-page: https://gitlab.com/felbeaver/metrics
Author: Roman Mazalov
Author-email: dellight55@gmail.com
License: UNKNOWN
Project-URL: Bug Tracker, https://gitlab.com/felbeaver/metrics/-/issues
Platform: UNKNOWN
Classifier: Programming Language :: Python :: 3
Classifier: License :: OSI Approved :: MIT License
Classifier: Operating System :: OS Independent
Requires-Python: >=3.7
License-File: LICENSE
Requires-Dist: libclang (>=11.0.1)
